si_dyno_reader/__init__.py
si_dyno_reader/core.py
si_dyno_reader/exceptions.py
si_dyno_reader-0.0.5.dist-info/METADATA
si_dyno_reader-0.0.5.dist-info/WHEEL
si_dyno_reader-0.0.5.dist-info/licenses/LICENSE
si_dyno_reader-0.0.5.dist-info/RECORD
