Metadata-Version: 2.4
Name: si-dyno-reader
Version: 0.0.5
Summary: Package to read SI Dyno Data
Project-URL: Homepage, https://github.com/lukzimmermann/SiDynoReader
Project-URL: Issues, https://github.com/lukzimmermann/SiDynoReader/issues
Author-email: Lukas Zimmermann <lukas.zimmermann@schoggipopcorn.ch>
License-Expression: MIT
License-File: LICENSE
Classifier: Operating System :: OS Independent
Classifier: Programming Language :: Python :: 3
Requires-Python: >=3.8
Requires-Dist: numpy>=1.20.0
